[{"begin_time":"1958-09-25T02:00:00","ename":"-","end_time":"1958-09-30T20:00:00","features":[{"geometry":{"coordinates":[118.8,15.8],"type":"Point"},"properties":{"forecast":[],"move_dir":null,"move_speed":null,"power":5,"pressure":1000,"radius10":null,"radius10_quad":null,"radius12":null,"radius12_quad":null,"radius7":null,"radius7_quad":null,"remark":"","speed":10,"strong":"","time":"1958-09-25T02:00:00"},"type":"Feature"},{"geometry":{"coordinates":[118.5,15.1],"type":"Point"},"properties":{"forecast":[],"move_dir":null,"move_speed":null,"power":5,"pressure":1000,"radius10":null,"radius10_quad":null,"radius12":null,"radius12_quad":null,"radius7":null,"radius7_quad":null,"remark":"","speed":10,"strong":"","time":"1958-09-25T08:00:00"},"type":"Feature"},{"geometry":{"coordinates":[118.4,14.5],"type":"Point"},"properties":{"forecast":[],"move_dir":null,"move_speed":null,"power":5,"pressure":1000,"radius10":null,"radius10_quad":null,"radius12":null,"radius12_quad":null,"radius7":null,"radius7_quad":null,"remark":"","speed":10,"strong":"","time":"1958-09-25T14:00:00"},"type":"Feature"},{"geometry":{"coordinates":[118.4,13.8],"type":"Point"},"properties":{"forecast":[],"move_dir":null,"move_speed":null,"power":5,"pressure":1000,"radius10":null,"radius10_quad":null,"radius12":null,"radius12_quad":null,"radius7":null,"radius7_quad":null,"remark":"","speed":10,"strong":"","time":"1958-09-25T20:00:00"},"type":"Feature"},{"geometry":{"coordinates":[118.3,13.3],"type":"Point"},"properties":{"forecast":[],"move_dir":null,"move_speed":null,"power":5,"pressure":1000,"radius10":null,"radius10_quad":null,"radius12":null,"radius12_quad":null,"radius7":null,"radius7_quad":null,"remark":"","speed":10,"strong":"","time":"1958-09-26T02:00:00"},"type":"Feature"},{"geometry":{"coordinates":[117.8,13],"type":"Point"},"properties":{"forecast":[],"move_dir":null,"move_speed":null,"power":7,"pressure":998,"radius10":null,"radius10_quad":null,"radius12":null,"radius12_quad":null,"radius7":null,"radius7_quad":null,"remark":"","speed":15,"strong":"热带低压(TD)","time":"1958-09-26T08:00:00"},"type":"Feature"},{"geometry":{"coordinates":[117.4,14],"type":"Point"},"properties":{"forecast":[],"move_dir":null,"move_speed":null,"power":7,"pressure":998,"radius10":null,"radius10_quad":null,"radius12":null,"radius12_quad":null,"radius7":null,"radius7_quad":null,"remark":"","speed":15,"strong":"热带低压(TD)","time":"1958-09-26T14:00:00"},"type":"Feature"},{"geometry":{"coordinates":[117.3,15.5],"type":"Point"},"properties":{"forecast":[],"move_dir":null,"move_speed":null,"power":7,"pressure":998,"radius10":null,"radius10_quad":null,"radius12":null,"radius12_quad":null,"radius7":null,"radius7_quad":null,"remark":"","speed":15,"strong":"热带低压(TD)","time":"1958-09-26T20:00:00"},"type":"Feature"},{"geometry":{"coordinates":[117.2,16.5],"type":"Point"},"properties":{"forecast":[],"move_dir":null,"move_speed":null,"power":7,"pressure":998,"radius10":null,"radius10_quad":null,"radius12":null,"radius12_quad":null,"radius7":null,"radius7_quad":null,"remark":"","speed":15,"strong":"热带低压(TD)","time":"1958-09-27T02:00:00"},"type":"Feature"},{"geometry":{"coordinates":[117.2,17.6],"type":"Point"},"properties":{"forecast":[],"move_dir":null,"move_speed":null,"power":7,"pressure":999,"radius10":null,"radius10_quad":null,"radius12":null,"radius12_quad":null,"radius7":null,"radius7_quad":null,"remark":"","speed":15,"strong":"热带低压(TD)","time":"1958-09-27T08:00:00"},"type":"Feature"},{"geometry":{"coordinates":[117.1,18.5],"type":"Point"},"properties":{"forecast":[],"move_dir":null,"move_speed":null,"power":7,"pressure":999,"radius10":null,"radius10_quad":null,"radius12":null,"radius12_quad":null,"radius7":null,"radius7_quad":null,"remark":"","speed":15,"strong":"热带低压(TD)","time":"1958-09-27T14:00:00"},"type":"Feature"},{"geometry":{"coordinates":[116.7,18.8],"type":"Point"},"properties":{"forecast":[],"move_dir":null,"move_speed":null,"power":7,"pressure":999,"radius10":null,"radius10_quad":null,"radius12":null,"radius12_quad":null,"radius7":null,"radius7_quad":null,"remark":"","speed":15,"strong":"热带低压(TD)","time":"1958-09-27T20:00:00"},"type":"Feature"},{"geometry":{"coordinates":[116.2,19],"type":"Point"},"properties":{"forecast":[],"move_dir":null,"move_speed":null,"power":7,"pressure":998,"radius10":null,"radius10_quad":null,"radius12":null,"radius12_quad":null,"radius7":null,"radius7_quad":null,"remark":"","speed":15,"strong":"热带低压(TD)","time":"1958-09-28T02:00:00"},"type":"Feature"},{"geometry":{"coordinates":[115.6,19.2],"type":"Point"},"properties":{"forecast":[],"move_dir":null,"move_speed":null,"power":7,"pressure":998,"radius10":null,"radius10_quad":null,"radius12":null,"radius12_quad":null,"radius7":null,"radius7_quad":null,"remark":"","speed":15,"strong":"热带低压(TD)","time":"1958-09-28T08:00:00"},"type":"Feature"},{"geometry":{"coordinates":[115.2,19.3],"type":"Point"},"properties":{"forecast":[],"move_dir":null,"move_speed":null,"power":8,"pressure":998,"radius10":null,"radius10_quad":null,"radius12":null,"radius12_quad":null,"radius7":null,"radius7_quad":null,"remark":"","speed":20,"strong":"热带风暴(TS)","time":"1958-09-28T14:00:00"},"type":"Feature"},{"geometry":{"coordinates":[114.8,19.5],"type":"Point"},"properties":{"forecast":[],"move_dir":null,"move_speed":null,"power":8,"pressure":998,"radius10":null,"radius10_quad":null,"radius12":null,"radius12_quad":null,"radius7":null,"radius7_quad":null,"remark":"","speed":20,"strong":"热带风暴(TS)","time":"1958-09-28T20:00:00"},"type":"Feature"},{"geometry":{"coordinates":[114.3,19.8],"type":"Point"},"properties":{"forecast":[],"move_dir":null,"move_speed":null,"power":8,"pressure":998,"radius10":null,"radius10_quad":null,"radius12":null,"radius12_quad":null,"radius7":null,"radius7_quad":null,"remark":"","speed":20,"strong":"热带风暴(TS)","time":"1958-09-29T02:00:00"},"type":"Feature"},{"geometry":{"coordinates":[114,20],"type":"Point"},"properties":{"forecast":[],"move_dir":null,"move_speed":null,"power":8,"pressure":1000,"radius10":null,"radius10_quad":null,"radius12":null,"radius12_quad":null,"radius7":null,"radius7_quad":null,"remark":"","speed":20,"strong":"热带风暴(TS)","time":"1958-09-29T08:00:00"},"type":"Feature"},{"geometry":{"coordinates":[113.6,20.2],"type":"Point"},"properties":{"forecast":[],"move_dir":null,"move_speed":null,"power":8,"pressure":1000,"radius10":null,"radius10_quad":null,"radius12":null,"radius12_quad":null,"radius7":null,"radius7_quad":null,"remark":"","speed":20,"strong":"热带风暴(TS)","time":"1958-09-29T14:00:00"},"type":"Feature"},{"geometry":{"coordinates":[113.1,20.3],"type":"Point"},"properties":{"forecast":[],"move_dir":null,"move_speed":null,"power":7,"pressure":1000,"radius10":null,"radius10_quad":null,"radius12":null,"radius12_quad":null,"radius7":null,"radius7_quad":null,"remark":"","speed":15,"strong":"热带低压(TD)","time":"1958-09-29T20:00:00"},"type":"Feature"},{"geometry":{"coordinates":[112.8,20.5],"type":"Point"},"properties":{"forecast":[],"move_dir":null,"move_speed":null,"power":7,"pressure":1004,"radius10":null,"radius10_quad":null,"radius12":null,"radius12_quad":null,"radius7":null,"radius7_quad":null,"remark":"","speed":15,"strong":"热带低压(TD)","time":"1958-09-30T02:00:00"},"type":"Feature"},{"geometry":{"coordinates":[112.4,20.6],"type":"Point"},"properties":{"forecast":[],"move_dir":null,"move_speed":null,"power":5,"pressure":1004,"radius10":null,"radius10_quad":null,"radius12":null,"radius12_quad":null,"radius7":null,"radius7_quad":null,"remark":"","speed":10,"strong":"","time":"1958-09-30T08:00:00"},"type":"Feature"},{"geometry":{"coordinates":[111.6,20.7],"type":"Point"},"properties":{"forecast":[],"move_dir":null,"move_speed":null,"power":5,"pressure":1005,"radius10":null,"radius10_quad":null,"radius12":null,"radius12_quad":null,"radius7":null,"radius7_quad":null,"remark":"","speed":10,"strong":"","time":"1958-09-30T14:00:00"},"type":"Feature"},{"geometry":{"coordinates":[110,20.8],"type":"Point"},"properties":{"forecast":[],"move_dir":null,"move_speed":null,"power":5,"pressure":1008,"radius10":null,"radius10_quad":null,"radius12":null,"radius12_quad":null,"radius7":null,"radius7_quad":null,"remark":"","speed":9,"strong":"","time":"1958-09-30T20:00:00"},"type":"Feature"}],"is_current":0,"land":[],"name":"-","tfbh":"195828","type":"FeatureCollection"}]