[{"begin_time":"1960-12-11T08:00:00","ename":"Phyllis","end_time":"1960-12-21T02:00:00","features":[{"geometry":{"coordinates":[146,7],"type":"Point"},"properties":{"forecast":[],"move_dir":null,"move_speed":null,"power":7,"pressure":1006,"radius10":null,"radius10_quad":null,"radius12":null,"radius12_quad":null,"radius7":null,"radius7_quad":null,"remark":"","speed":15,"strong":"热带低压(TD)","time":"1960-12-11T08:00:00"},"type":"Feature"},{"geometry":{"coordinates":[146.5,7.5],"type":"Point"},"properties":{"forecast":[],"move_dir":null,"move_speed":null,"power":7,"pressure":1002,"radius10":null,"radius10_quad":null,"radius12":null,"radius12_quad":null,"radius7":null,"radius7_quad":null,"remark":"","speed":15,"strong":"热带低压(TD)","time":"1960-12-11T14:00:00"},"type":"Feature"},{"geometry":{"coordinates":[146.4,8],"type":"Point"},"properties":{"forecast":[],"move_dir":null,"move_speed":null,"power":7,"pressure":1002,"radius10":null,"radius10_quad":null,"radius12":null,"radius12_quad":null,"radius7":null,"radius7_quad":null,"remark":"","speed":15,"strong":"热带低压(TD)","time":"1960-12-11T20:00:00"},"type":"Feature"},{"geometry":{"coordinates":[145.6,9.2],"type":"Point"},"properties":{"forecast":[],"move_dir":null,"move_speed":null,"power":7,"pressure":1000,"radius10":null,"radius10_quad":null,"radius12":null,"radius12_quad":null,"radius7":null,"radius7_quad":null,"remark":"","speed":15,"strong":"热带低压(TD)","time":"1960-12-12T02:00:00"},"type":"Feature"},{"geometry":{"coordinates":[144,9.8],"type":"Point"},"properties":{"forecast":[],"move_dir":null,"move_speed":null,"power":8,"pressure":1000,"radius10":null,"radius10_quad":null,"radius12":null,"radius12_quad":null,"radius7":null,"radius7_quad":null,"remark":"","speed":20,"strong":"热带风暴(TS)","time":"1960-12-12T08:00:00"},"type":"Feature"},{"geometry":{"coordinates":[142,10.1],"type":"Point"},"properties":{"forecast":[],"move_dir":null,"move_speed":null,"power":8,"pressure":1000,"radius10":null,"radius10_quad":null,"radius12":null,"radius12_quad":null,"radius7":null,"radius7_quad":null,"remark":"","speed":20,"strong":"热带风暴(TS)","time":"1960-12-12T14:00:00"},"type":"Feature"},{"geometry":{"coordinates":[140.2,10.5],"type":"Point"},"properties":{"forecast":[],"move_dir":null,"move_speed":null,"power":8,"pressure":1000,"radius10":null,"radius10_quad":null,"radius12":null,"radius12_quad":null,"radius7":null,"radius7_quad":null,"remark":"","speed":20,"strong":"热带风暴(TS)","time":"1960-12-12T20:00:00"},"type":"Feature"},{"geometry":{"coordinates":[138,11.1],"type":"Point"},"properties":{"forecast":[],"move_dir":null,"move_speed":null,"power":10,"pressure":998,"radius10":null,"radius10_quad":null,"radius12":null,"radius12_quad":null,"radius7":null,"radius7_quad":null,"remark":"","speed":25,"strong":"强热带风暴(STS)","time":"1960-12-13T02:00:00"},"type":"Feature"},{"geometry":{"coordinates":[135.7,11.8],"type":"Point"},"properties":{"forecast":[],"move_dir":null,"move_speed":null,"power":11,"pressure":994,"radius10":null,"radius10_quad":null,"radius12":null,"radius12_quad":null,"radius7":null,"radius7_quad":null,"remark":"","speed":30,"strong":"强热带风暴(STS)","time":"1960-12-13T08:00:00"},"type":"Feature"},{"geometry":{"coordinates":[134.5,11.7],"type":"Point"},"properties":{"forecast":[],"move_dir":null,"move_speed":null,"power":12,"pressure":984,"radius10":null,"radius10_quad":null,"radius12":null,"radius12_quad":null,"radius7":null,"radius7_quad":null,"remark":"","speed":35,"strong":"台风(TY)","time":"1960-12-13T14:00:00"},"type":"Feature"},{"geometry":{"coordinates":[134,12.1],"type":"Point"},"properties":{"forecast":[],"move_dir":null,"move_speed":null,"power":12,"pressure":983,"radius10":null,"radius10_quad":null,"radius12":null,"radius12_quad":null,"radius7":null,"radius7_quad":null,"remark":"","speed":35,"strong":"台风(TY)","time":"1960-12-13T20:00:00"},"type":"Feature"},{"geometry":{"coordinates":[133.6,12.6],"type":"Point"},"properties":{"forecast":[],"move_dir":null,"move_speed":null,"power":12,"pressure":981,"radius10":null,"radius10_quad":null,"radius12":null,"radius12_quad":null,"radius7":null,"radius7_quad":null,"remark":"","speed":35,"strong":"台风(TY)","time":"1960-12-14T02:00:00"},"type":"Feature"},{"geometry":{"coordinates":[133.2,13.1],"type":"Point"},"properties":{"forecast":[],"move_dir":null,"move_speed":null,"power":12,"pressure":980,"radius10":null,"radius10_quad":null,"radius12":null,"radius12_quad":null,"radius7":null,"radius7_quad":null,"remark":"","speed":35,"strong":"台风(TY)","time":"1960-12-14T08:00:00"},"type":"Feature"},{"geometry":{"coordinates":[132.9,13.4],"type":"Point"},"properties":{"forecast":[],"move_dir":null,"move_speed":null,"power":12,"pressure":980,"radius10":null,"radius10_quad":null,"radius12":null,"radius12_quad":null,"radius7":null,"radius7_quad":null,"remark":"","speed":35,"strong":"台风(TY)","time":"1960-12-14T14:00:00"},"type":"Feature"},{"geometry":{"coordinates":[132.8,13.6],"type":"Point"},"properties":{"forecast":[],"move_dir":null,"move_speed":null,"power":12,"pressure":982,"radius10":null,"radius10_quad":null,"radius12":null,"radius12_quad":null,"radius7":null,"radius7_quad":null,"remark":"","speed":35,"strong":"台风(TY)","time":"1960-12-14T20:00:00"},"type":"Feature"},{"geometry":{"coordinates":[132.7,13.8],"type":"Point"},"properties":{"forecast":[],"move_dir":null,"move_speed":null,"power":12,"pressure":985,"radius10":null,"radius10_quad":null,"radius12":null,"radius12_quad":null,"radius7":null,"radius7_quad":null,"remark":"","speed":35,"strong":"台风(TY)","time":"1960-12-15T02:00:00"},"type":"Feature"},{"geometry":{"coordinates":[132.6,13.9],"type":"Point"},"properties":{"forecast":[],"move_dir":null,"move_speed":null,"power":12,"pressure":988,"radius10":null,"radius10_quad":null,"radius12":null,"radius12_quad":null,"radius7":null,"radius7_quad":null,"remark":"","speed":35,"strong":"台风(TY)","time":"1960-12-15T08:00:00"},"type":"Feature"},{"geometry":{"coordinates":[132.7,14.8],"type":"Point"},"properties":{"forecast":[],"move_dir":null,"move_speed":null,"power":12,"pressure":987,"radius10":null,"radius10_quad":null,"radius12":null,"radius12_quad":null,"radius7":null,"radius7_quad":null,"remark":"","speed":35,"strong":"台风(TY)","time":"1960-12-15T14:00:00"},"type":"Feature"},{"geometry":{"coordinates":[132.3,14.7],"type":"Point"},"properties":{"forecast":[],"move_dir":null,"move_speed":null,"power":12,"pressure":985,"radius10":null,"radius10_quad":null,"radius12":null,"radius12_quad":null,"radius7":null,"radius7_quad":null,"remark":"","speed":35,"strong":"台风(TY)","time":"1960-12-15T20:00:00"},"type":"Feature"},{"geometry":{"coordinates":[131.4,15],"type":"Point"},"properties":{"forecast":[],"move_dir":null,"move_speed":null,"power":12,"pressure":984,"radius10":null,"radius10_quad":null,"radius12":null,"radius12_quad":null,"radius7":null,"radius7_quad":null,"remark":"","speed":35,"strong":"台风(TY)","time":"1960-12-16T02:00:00"},"type":"Feature"},{"geometry":{"coordinates":[130.3,15],"type":"Point"},"properties":{"forecast":[],"move_dir":null,"move_speed":null,"power":12,"pressure":983,"radius10":null,"radius10_quad":null,"radius12":null,"radius12_quad":null,"radius7":null,"radius7_quad":null,"remark":"","speed":35,"strong":"台风(TY)","time":"1960-12-16T08:00:00"},"type":"Feature"},{"geometry":{"coordinates":[129.3,15.2],"type":"Point"},"properties":{"forecast":[],"move_dir":null,"move_speed":null,"power":12,"pressure":977,"radius10":null,"radius10_quad":null,"radius12":null,"radius12_quad":null,"radius7":null,"radius7_quad":null,"remark":"","speed":35,"strong":"台风(TY)","time":"1960-12-16T14:00:00"},"type":"Feature"},{"geometry":{"coordinates":[128.3,15.3],"type":"Point"},"properties":{"forecast":[],"move_dir":null,"move_speed":null,"power":12,"pressure":976,"radius10":null,"radius10_quad":null,"radius12":null,"radius12_quad":null,"radius7":null,"radius7_quad":null,"remark":"","speed":35,"strong":"台风(TY)","time":"1960-12-16T20:00:00"},"type":"Feature"},{"geometry":{"coordinates":[127.2,15.4],"type":"Point"},"properties":{"forecast":[],"move_dir":null,"move_speed":null,"power":13,"pressure":975,"radius10":null,"radius10_quad":null,"radius12":null,"radius12_quad":null,"radius7":null,"radius7_quad":null,"remark":"","speed":40,"strong":"台风(TY)","time":"1960-12-17T02:00:00"},"type":"Feature"},{"geometry":{"coordinates":[126.2,15.5],"type":"Point"},"properties":{"forecast":[],"move_dir":null,"move_speed":null,"power":13,"pressure":975,"radius10":null,"radius10_quad":null,"radius12":null,"radius12_quad":null,"radius7":null,"radius7_quad":null,"remark":"","speed":40,"strong":"台风(TY)","time":"1960-12-17T08:00:00"},"type":"Feature"},{"geometry":{"coordinates":[125.6,15.8],"type":"Point"},"properties":{"forecast":[],"move_dir":null,"move_speed":null,"power":13,"pressure":974,"radius10":null,"radius10_quad":null,"radius12":null,"radius12_quad":null,"radius7":null,"radius7_quad":null,"remark":"","speed":40,"strong":"台风(TY)","time":"1960-12-17T14:00:00"},"type":"Feature"},{"geometry":{"coordinates":[125,16.5],"type":"Point"},"properties":{"forecast":[],"move_dir":null,"move_speed":null,"power":14,"pressure":972,"radius10":null,"radius10_quad":null,"radius12":null,"radius12_quad":null,"radius7":null,"radius7_quad":null,"remark":"","speed":45,"strong":"强台风(STY)","time":"1960-12-17T20:00:00"},"type":"Feature"},{"geometry":{"coordinates":[124.4,17],"type":"Point"},"properties":{"forecast":[],"move_dir":null,"move_speed":null,"power":14,"pressure":972,"radius10":null,"radius10_quad":null,"radius12":null,"radius12_quad":null,"radius7":null,"radius7_quad":null,"remark":"","speed":45,"strong":"强台风(STY)","time":"1960-12-18T02:00:00"},"type":"Feature"},{"geometry":{"coordinates":[124.3,17.3],"type":"Point"},"properties":{"forecast":[],"move_dir":null,"move_speed":null,"power":15,"pressure":970,"radius10":null,"radius10_quad":null,"radius12":null,"radius12_quad":null,"radius7":null,"radius7_quad":null,"remark":"","speed":50,"strong":"强台风(STY)","time":"1960-12-18T08:00:00"},"type":"Feature"},{"geometry":{"coordinates":[124.2,17.4],"type":"Point"},"properties":{"forecast":[],"move_dir":null,"move_speed":null,"power":16,"pressure":965,"radius10":null,"radius10_quad":null,"radius12":null,"radius12_quad":null,"radius7":null,"radius7_quad":null,"remark":"","speed":55,"strong":"超强台风(Super TY)","time":"1960-12-18T14:00:00"},"type":"Feature"},{"geometry":{"coordinates":[124.4,17.7],"type":"Point"},"properties":{"forecast":[],"move_dir":null,"move_speed":null,"power":16,"pressure":969,"radius10":null,"radius10_quad":null,"radius12":null,"radius12_quad":null,"radius7":null,"radius7_quad":null,"remark":"","speed":55,"strong":"超强台风(Super TY)","time":"1960-12-18T20:00:00"},"type":"Feature"},{"geometry":{"coordinates":[124.9,17.8],"type":"Point"},"properties":{"forecast":[],"move_dir":null,"move_speed":null,"power":15,"pressure":974,"radius10":null,"radius10_quad":null,"radius12":null,"radius12_quad":null,"radius7":null,"radius7_quad":null,"remark":"","speed":50,"strong":"强台风(STY)","time":"1960-12-19T02:00:00"},"type":"Feature"},{"geometry":{"coordinates":[125.4,17.8],"type":"Point"},"properties":{"forecast":[],"move_dir":null,"move_speed":null,"power":14,"pressure":980,"radius10":null,"radius10_quad":null,"radius12":null,"radius12_quad":null,"radius7":null,"radius7_quad":null,"remark":"","speed":45,"strong":"强台风(STY)","time":"1960-12-19T08:00:00"},"type":"Feature"},{"geometry":{"coordinates":[125.8,17.7],"type":"Point"},"properties":{"forecast":[],"move_dir":null,"move_speed":null,"power":13,"pressure":989,"radius10":null,"radius10_quad":null,"radius12":null,"radius12_quad":null,"radius7":null,"radius7_quad":null,"remark":"","speed":40,"strong":"台风(TY)","time":"1960-12-19T14:00:00"},"type":"Feature"},{"geometry":{"coordinates":[126.3,17.8],"type":"Point"},"properties":{"forecast":[],"move_dir":null,"move_speed":null,"power":12,"pressure":992,"radius10":null,"radius10_quad":null,"radius12":null,"radius12_quad":null,"radius7":null,"radius7_quad":null,"remark":"","speed":35,"strong":"台风(TY)","time":"1960-12-19T20:00:00"},"type":"Feature"},{"geometry":{"coordinates":[127,17.9],"type":"Point"},"properties":{"forecast":[],"move_dir":null,"move_speed":null,"power":10,"pressure":995,"radius10":null,"radius10_quad":null,"radius12":null,"radius12_quad":null,"radius7":null,"radius7_quad":null,"remark":"","speed":25,"strong":"强热带风暴(STS)","time":"1960-12-20T02:00:00"},"type":"Feature"},{"geometry":{"coordinates":[127.8,17.9],"type":"Point"},"properties":{"forecast":[],"move_dir":null,"move_speed":null,"power":7,"pressure":1000,"radius10":null,"radius10_quad":null,"radius12":null,"radius12_quad":null,"radius7":null,"radius7_quad":null,"remark":"","speed":15,"strong":"热带低压(TD)","time":"1960-12-20T08:00:00"},"type":"Feature"},{"geometry":{"coordinates":[129.5,18.2],"type":"Point"},"properties":{"forecast":[],"move_dir":null,"move_speed":null,"power":7,"pressure":1006,"radius10":null,"radius10_quad":null,"radius12":null,"radius12_quad":null,"radius7":null,"radius7_quad":null,"remark":"","speed":15,"strong":"热带低压(TD)","time":"1960-12-20T14:00:00"},"type":"Feature"},{"geometry":{"coordinates":[132,18.5],"type":"Point"},"properties":{"forecast":[],"move_dir":null,"move_speed":null,"power":5,"pressure":1010,"radius10":null,"radius10_quad":null,"radius12":null,"radius12_quad":null,"radius7":null,"radius7_quad":null,"remark":"","speed":10,"strong":"","time":"1960-12-20T20:00:00"},"type":"Feature"},{"geometry":{"coordinates":[134.4,19],"type":"Point"},"properties":{"forecast":[],"move_dir":null,"move_speed":null,"power":0,"pressure":1010,"radius10":null,"radius10_quad":null,"radius12":null,"radius12_quad":null,"radius7":null,"radius7_quad":null,"remark":"","speed":0,"strong":"","time":"1960-12-21T02:00:00"},"type":"Feature"}],"is_current":0,"land":[],"name":"-","tfbh":"196028","type":"FeatureCollection"}]