[{"begin_time":"2008-09-29T02:00:00","ename":"MEKKHALA","end_time":"2008-09-30T23:00:00","features":[{"geometry":{"coordinates":[112.3,15.3],"type":"Point"},"properties":{"forecast":[],"move_dir":"西北","move_speed":10,"power":7,"pressure":998,"radius10":null,"radius10_quad":null,"radius12":null,"radius12_quad":null,"radius7":100,"radius7_quad":null,"remark":"","speed":16,"strong":"热带低压(TD)","time":"2008-09-29T02:00:00"},"type":"Feature"},{"geometry":{"coordinates":[112,15.7],"type":"Point"},"properties":{"forecast":[],"move_dir":"西北西","move_speed":10,"power":7,"pressure":998,"radius10":null,"radius10_quad":null,"radius12":null,"radius12_quad":null,"radius7":100,"radius7_quad":null,"remark":"","speed":16,"strong":"热带低压(TD)","time":"2008-09-29T05:00:00"},"type":"Feature"},{"geometry":{"coordinates":[111.8,16.5],"type":"Point"},"properties":{"forecast":[],"move_dir":"西北","move_speed":10,"power":8,"pressure":992,"radius10":null,"radius10_quad":null,"radius12":null,"radius12_quad":null,"radius7":100,"radius7_quad":null,"remark":"","speed":18,"strong":"热带风暴(TS)","time":"2008-09-29T08:00:00"},"type":"Feature"},{"geometry":{"coordinates":[111.4,16.5],"type":"Point"},"properties":{"forecast":[],"move_dir":"西北","move_speed":10,"power":8,"pressure":992,"radius10":null,"radius10_quad":null,"radius12":null,"radius12_quad":null,"radius7":100,"radius7_quad":null,"remark":"","speed":18,"strong":"热带风暴(TS)","time":"2008-09-29T10:00:00"},"type":"Feature"},{"geometry":{"coordinates":[111.4,16.5],"type":"Point"},"properties":{"forecast":[],"move_dir":"西北","move_speed":10,"power":8,"pressure":990,"radius10":null,"radius10_quad":null,"radius12":null,"radius12_quad":null,"radius7":100,"radius7_quad":null,"remark":"","speed":20,"strong":"热带风暴(TS)","time":"2008-09-29T11:00:00"},"type":"Feature"},{"geometry":{"coordinates":[111.4,16.5],"type":"Point"},"properties":{"forecast":[],"move_dir":"西北","move_speed":10,"power":8,"pressure":990,"radius10":null,"radius10_quad":null,"radius12":null,"radius12_quad":null,"radius7":100,"radius7_quad":null,"remark":"","speed":20,"strong":"热带风暴(TS)","time":"2008-09-29T12:00:00"},"type":"Feature"},{"geometry":{"coordinates":[111.3,16.5],"type":"Point"},"properties":{"forecast":[],"move_dir":"西西北","move_speed":10,"power":8,"pressure":990,"radius10":null,"radius10_quad":null,"radius12":null,"radius12_quad":null,"radius7":100,"radius7_quad":null,"remark":"","speed":20,"strong":"热带风暴(TS)","time":"2008-09-29T13:00:00"},"type":"Feature"},{"geometry":{"coordinates":[110.9,16.5],"type":"Point"},"properties":{"forecast":[],"move_dir":"西北","move_speed":10,"power":8,"pressure":990,"radius10":null,"radius10_quad":null,"radius12":null,"radius12_quad":null,"radius7":100,"radius7_quad":null,"remark":"","speed":20,"strong":"热带风暴(TS)","time":"2008-09-29T14:00:00"},"type":"Feature"},{"geometry":{"coordinates":[110.8,16.5],"type":"Point"},"properties":{"forecast":[],"move_dir":"西北","move_speed":10,"power":8,"pressure":990,"radius10":null,"radius10_quad":null,"radius12":null,"radius12_quad":null,"radius7":100,"radius7_quad":null,"remark":"","speed":20,"strong":"热带风暴(TS)","time":"2008-09-29T15:00:00"},"type":"Feature"},{"geometry":{"coordinates":[110.7,16.8],"type":"Point"},"properties":{"forecast":[],"move_dir":"西北","move_speed":10,"power":8,"pressure":990,"radius10":null,"radius10_quad":null,"radius12":null,"radius12_quad":null,"radius7":100,"radius7_quad":null,"remark":"","speed":20,"strong":"热带风暴(TS)","time":"2008-09-29T16:00:00"},"type":"Feature"},{"geometry":{"coordinates":[110.5,16.9],"type":"Point"},"properties":{"forecast":[],"move_dir":"西北","move_speed":15,"power":8,"pressure":990,"radius10":null,"radius10_quad":null,"radius12":null,"radius12_quad":null,"radius7":120,"radius7_quad":null,"remark":"","speed":20,"strong":"热带风暴(TS)","time":"2008-09-29T17:00:00"},"type":"Feature"},{"geometry":{"coordinates":[110.1,17],"type":"Point"},"properties":{"forecast":[],"move_dir":"西北","move_speed":15,"power":8,"pressure":990,"radius10":null,"radius10_quad":null,"radius12":null,"radius12_quad":null,"radius7":150,"radius7_quad":null,"remark":"","speed":20,"strong":"热带风暴(TS)","time":"2008-09-29T18:00:00"},"type":"Feature"},{"geometry":{"coordinates":[109.7,17.2],"type":"Point"},"properties":{"forecast":[],"move_dir":"西北","move_speed":20,"power":9,"pressure":990,"radius10":null,"radius10_quad":null,"radius12":null,"radius12_quad":null,"radius7":180,"radius7_quad":null,"remark":"","speed":23,"strong":"热带风暴(TS)","time":"2008-09-29T19:00:00"},"type":"Feature"},{"geometry":{"coordinates":[109.6,17.4],"type":"Point"},"properties":{"forecast":[],"move_dir":"北","move_speed":null,"power":9,"pressure":990,"radius10":null,"radius10_quad":null,"radius12":null,"radius12_quad":null,"radius7":200,"radius7_quad":null,"remark":"","speed":23,"strong":"热带风暴(TS)","time":"2008-09-29T20:00:00"},"type":"Feature"},{"geometry":{"coordinates":[109.4,17.4],"type":"Point"},"properties":{"forecast":[],"move_dir":"西西北","move_speed":20,"power":9,"pressure":990,"radius10":null,"radius10_quad":null,"radius12":null,"radius12_quad":null,"radius7":200,"radius7_quad":null,"remark":"","speed":23,"strong":"热带风暴(TS)","time":"2008-09-29T21:00:00"},"type":"Feature"},{"geometry":{"coordinates":[109.2,17.4],"type":"Point"},"properties":{"forecast":[],"move_dir":"西西北","move_speed":20,"power":9,"pressure":990,"radius10":null,"radius10_quad":null,"radius12":null,"radius12_quad":null,"radius7":200,"radius7_quad":null,"remark":"","speed":23,"strong":"热带风暴(TS)","time":"2008-09-29T22:00:00"},"type":"Feature"},{"geometry":{"coordinates":[109,17.4],"type":"Point"},"properties":{"forecast":[],"move_dir":"西西北","move_speed":20,"power":9,"pressure":990,"radius10":null,"radius10_quad":null,"radius12":null,"radius12_quad":null,"radius7":200,"radius7_quad":null,"remark":"","speed":23,"strong":"热带风暴(TS)","time":"2008-09-29T23:00:00"},"type":"Feature"},{"geometry":{"coordinates":[108.8,17.4],"type":"Point"},"properties":{"forecast":[],"move_dir":"西西北","move_speed":20,"power":9,"pressure":990,"radius10":null,"radius10_quad":null,"radius12":null,"radius12_quad":null,"radius7":200,"radius7_quad":null,"remark":"","speed":23,"strong":"热带风暴(TS)","time":"2008-09-30T00:00:00"},"type":"Feature"},{"geometry":{"coordinates":[108.5,17.4],"type":"Point"},"properties":{"forecast":[],"move_dir":"西","move_speed":20,"power":9,"pressure":990,"radius10":null,"radius10_quad":null,"radius12":null,"radius12_quad":null,"radius7":200,"radius7_quad":null,"remark":"","speed":23,"strong":"热带风暴(TS)","time":"2008-09-30T01:00:00"},"type":"Feature"},{"geometry":{"coordinates":[108.2,17.4],"type":"Point"},"properties":{"forecast":[],"move_dir":"西","move_speed":20,"power":9,"pressure":990,"radius10":null,"radius10_quad":null,"radius12":null,"radius12_quad":null,"radius7":200,"radius7_quad":null,"remark":"","speed":23,"strong":"热带风暴(TS)","time":"2008-09-30T02:00:00"},"type":"Feature"},{"geometry":{"coordinates":[108,17.4],"type":"Point"},"properties":{"forecast":[],"move_dir":"西","move_speed":20,"power":9,"pressure":990,"radius10":null,"radius10_quad":null,"radius12":null,"radius12_quad":null,"radius7":200,"radius7_quad":null,"remark":"","speed":23,"strong":"热带风暴(TS)","time":"2008-09-30T03:00:00"},"type":"Feature"},{"geometry":{"coordinates":[107.7,17.5],"type":"Point"},"properties":{"forecast":[],"move_dir":"西","move_speed":20,"power":9,"pressure":990,"radius10":null,"radius10_quad":null,"radius12":null,"radius12_quad":null,"radius7":200,"radius7_quad":null,"remark":"","speed":23,"strong":"热带风暴(TS)","time":"2008-09-30T04:00:00"},"type":"Feature"},{"geometry":{"coordinates":[107.6,17.5],"type":"Point"},"properties":{"forecast":[],"move_dir":"西","move_speed":20,"power":9,"pressure":990,"radius10":null,"radius10_quad":null,"radius12":null,"radius12_quad":null,"radius7":200,"radius7_quad":null,"remark":"","speed":23,"strong":"热带风暴(TS)","time":"2008-09-30T05:00:00"},"type":"Feature"},{"geometry":{"coordinates":[107.4,17.5],"type":"Point"},"properties":{"forecast":[],"move_dir":"西","move_speed":20,"power":9,"pressure":990,"radius10":null,"radius10_quad":null,"radius12":null,"radius12_quad":null,"radius7":200,"radius7_quad":null,"remark":"","speed":23,"strong":"热带风暴(TS)","time":"2008-09-30T06:00:00"},"type":"Feature"},{"geometry":{"coordinates":[107.3,17.5],"type":"Point"},"properties":{"forecast":[],"move_dir":"西","move_speed":15,"power":9,"pressure":990,"radius10":null,"radius10_quad":null,"radius12":null,"radius12_quad":null,"radius7":200,"radius7_quad":null,"remark":"","speed":23,"strong":"热带风暴(TS)","time":"2008-09-30T07:00:00"},"type":"Feature"},{"geometry":{"coordinates":[107,17.5],"type":"Point"},"properties":{"forecast":[],"move_dir":"北","move_speed":null,"power":9,"pressure":990,"radius10":null,"radius10_quad":null,"radius12":null,"radius12_quad":null,"radius7":200,"radius7_quad":null,"remark":"","speed":23,"strong":"热带风暴(TS)","time":"2008-09-30T08:00:00"},"type":"Feature"},{"geometry":{"coordinates":[106.8,17.4],"type":"Point"},"properties":{"forecast":[],"move_dir":"西","move_speed":15,"power":9,"pressure":990,"radius10":null,"radius10_quad":null,"radius12":null,"radius12_quad":null,"radius7":200,"radius7_quad":null,"remark":"","speed":23,"strong":"热带风暴(TS)","time":"2008-09-30T09:00:00"},"type":"Feature"},{"geometry":{"coordinates":[106.6,17.4],"type":"Point"},"properties":{"forecast":[],"move_dir":"西","move_speed":15,"power":9,"pressure":990,"radius10":null,"radius10_quad":null,"radius12":null,"radius12_quad":null,"radius7":200,"radius7_quad":null,"remark":"","speed":23,"strong":"热带风暴(TS)","time":"2008-09-30T10:00:00"},"type":"Feature"},{"geometry":{"coordinates":[106.4,17.4],"type":"Point"},"properties":{"forecast":[],"move_dir":"西","move_speed":15,"power":9,"pressure":990,"radius10":null,"radius10_quad":null,"radius12":null,"radius12_quad":null,"radius7":200,"radius7_quad":null,"remark":"","speed":23,"strong":"热带风暴(TS)","time":"2008-09-30T11:00:00"},"type":"Feature"},{"geometry":{"coordinates":[106.2,17.5],"type":"Point"},"properties":{"forecast":[],"move_dir":"西","move_speed":20,"power":9,"pressure":990,"radius10":null,"radius10_quad":null,"radius12":null,"radius12_quad":null,"radius7":200,"radius7_quad":null,"remark":"","speed":23,"strong":"热带风暴(TS)","time":"2008-09-30T12:00:00"},"type":"Feature"},{"geometry":{"coordinates":[105.9,17.6],"type":"Point"},"properties":{"forecast":[],"move_dir":"西","move_speed":25,"power":9,"pressure":990,"radius10":null,"radius10_quad":null,"radius12":null,"radius12_quad":null,"radius7":200,"radius7_quad":null,"remark":"","speed":23,"strong":"热带风暴(TS)","time":"2008-09-30T13:00:00"},"type":"Feature"},{"geometry":{"coordinates":[105.3,18],"type":"Point"},"properties":{"forecast":[],"move_dir":"西","move_speed":25,"power":9,"pressure":990,"radius10":null,"radius10_quad":null,"radius12":null,"radius12_quad":null,"radius7":200,"radius7_quad":null,"remark":"","speed":23,"strong":"热带风暴(TS)","time":"2008-09-30T14:00:00"},"type":"Feature"},{"geometry":{"coordinates":[105.1,18.1],"type":"Point"},"properties":{"forecast":[],"move_dir":"西","move_speed":25,"power":9,"pressure":990,"radius10":null,"radius10_quad":null,"radius12":null,"radius12_quad":null,"radius7":200,"radius7_quad":null,"remark":"","speed":23,"strong":"热带风暴(TS)","time":"2008-09-30T15:00:00"},"type":"Feature"},{"geometry":{"coordinates":[104.7,18.2],"type":"Point"},"properties":{"forecast":[],"move_dir":"西","move_speed":25,"power":9,"pressure":990,"radius10":null,"radius10_quad":null,"radius12":null,"radius12_quad":null,"radius7":200,"radius7_quad":null,"remark":"","speed":23,"strong":"热带风暴(TS)","time":"2008-09-30T16:00:00"},"type":"Feature"},{"geometry":{"coordinates":[104.3,18.4],"type":"Point"},"properties":{"forecast":[],"move_dir":"西西北","move_speed":25,"power":9,"pressure":990,"radius10":null,"radius10_quad":null,"radius12":null,"radius12_quad":null,"radius7":200,"radius7_quad":null,"remark":"","speed":23,"strong":"热带风暴(TS)","time":"2008-09-30T17:00:00"},"type":"Feature"},{"geometry":{"coordinates":[104,18.5],"type":"Point"},"properties":{"forecast":[],"move_dir":"西西北","move_speed":25,"power":8,"pressure":992,"radius10":null,"radius10_quad":null,"radius12":null,"radius12_quad":null,"radius7":180,"radius7_quad":null,"remark":"","speed":20,"strong":"热带风暴(TS)","time":"2008-09-30T18:00:00"},"type":"Feature"},{"geometry":{"coordinates":[103.5,18.9],"type":"Point"},"properties":{"forecast":[],"move_dir":"西西北","move_speed":40,"power":8,"pressure":992,"radius10":null,"radius10_quad":null,"radius12":null,"radius12_quad":null,"radius7":180,"radius7_quad":null,"remark":"","speed":20,"strong":"热带风暴(TS)","time":"2008-09-30T19:00:00"},"type":"Feature"},{"geometry":{"coordinates":[102.6,19.1],"type":"Point"},"properties":{"forecast":[],"move_dir":"西西北","move_speed":40,"power":8,"pressure":995,"radius10":null,"radius10_quad":null,"radius12":null,"radius12_quad":null,"radius7":120,"radius7_quad":null,"remark":"","speed":18,"strong":"热带风暴(TS)","time":"2008-09-30T20:00:00"},"type":"Feature"},{"geometry":{"coordinates":[102.3,19.1],"type":"Point"},"properties":{"forecast":[],"move_dir":"西西北","move_speed":30,"power":8,"pressure":995,"radius10":null,"radius10_quad":null,"radius12":null,"radius12_quad":null,"radius7":120,"radius7_quad":null,"remark":"","speed":18,"strong":"热带风暴(TS)","time":"2008-09-30T21:00:00"},"type":"Feature"},{"geometry":{"coordinates":[102.1,19.2],"type":"Point"},"properties":{"forecast":[],"move_dir":"西西北","move_speed":25,"power":8,"pressure":995,"radius10":null,"radius10_quad":null,"radius12":null,"radius12_quad":null,"radius7":120,"radius7_quad":null,"remark":"","speed":18,"strong":"热带风暴(TS)","time":"2008-09-30T22:00:00"},"type":"Feature"},{"geometry":{"coordinates":[101.7,19.3],"type":"Point"},"properties":{"forecast":[],"move_dir":"西西北","move_speed":40,"power":8,"pressure":995,"radius10":null,"radius10_quad":null,"radius12":null,"radius12_quad":null,"radius7":120,"radius7_quad":null,"remark":"","speed":18,"strong":"热带风暴(TS)","time":"2008-09-30T23:00:00"},"type":"Feature"}],"is_current":0,"land":[],"name":"米克拉","tfbh":"200816","type":"FeatureCollection"}]